mcp_forge/__init__.py
mcp_forge/cli.py
mcp_forge/generators/base.py
mcp_forge/templates/core/__init__.py.j2
mcp_forge/templates/core/server.py.j2
mcp_forge/templates/core/server_http.py.j2
mcp_forge/templates/core/server_stdio.py.j2
mcp_forge/templates/interfaces/__init__.py.j2
mcp_forge/templates/interfaces/prompt.py.j2
mcp_forge/templates/interfaces/resource.py.j2
mcp_forge/templates/interfaces/tool.py.j2
mcp_forge/templates/prompts/__init__.py.j2
mcp_forge/templates/prompts/code_review.py.j2
mcp_forge/templates/prompts/data_analysis.py.j2
mcp_forge/templates/prompts/debug_assistant.py.j2
mcp_forge/templates/resources/__init__.py.j2
mcp_forge/templates/resources/hello_world.py.j2
mcp_forge/templates/resources/user_profile.py.j2
mcp_forge/templates/root/README.md.j2
mcp_forge/templates/root/demo_client.py.j2
mcp_forge/templates/root/demo_tools.py.j2
mcp_forge/templates/root/pyproject.toml.j2
mcp_forge/templates/services/__init__.py.j2
mcp_forge/templates/services/prompt_service.py.j2
mcp_forge/templates/services/resource_service.py.j2
mcp_forge/templates/services/tool_service.py.j2
mcp_forge/templates/tools/__init__.py.j2
mcp_forge/templates/tools/add_numbers.py.j2
mcp_forge/templates/tools/current_time.py.j2
mcp_forge/templates/tools/date_difference.py.j2
mcp_forge/templates/tools/random_number.py.j2
mcp_forge/templates/tools/reverse_string.py.j2
mcp_forge/utils/template.py
mcp_forge-0.3.0.dist-info/METADATA
mcp_forge-0.3.0.dist-info/WHEEL
mcp_forge-0.3.0.dist-info/entry_points.txt
mcp_forge-0.3.0.dist-info/licenses/LICENSE
mcp_forge-0.3.0.dist-info/RECORD
