Metadata-Version: 2.4
Name: mcp-forge
Version: 0.3.0
Summary: Scaffolding tool for Model Context Protocol (MCP) servers
License-File: LICENSE
Requires-Python: >=3.10
Requires-Dist: click>=8.0.0
Requires-Dist: jinja2>=3.0.0
Requires-Dist: rich>=10.0.0
